blueye/legacyprotocol/__init__.py
blueye/legacyprotocol/exceptions.py
blueye/legacyprotocol/tcp_client.py
blueye/legacyprotocol/tcp_protocol_class.py
blueye/legacyprotocol/udp_client.py
blueye/legacyprotocol/udp_protocol_dict.py
blueye/legacyprotocol/udp_protocol_parser.py
blueye_legacyprotocol-1.0.0.dist-info/licenses/LICENSE
tests/__init__.py
tests/test_protocol.py
tests/test_protocol_data.py
tests/test_tcp_client.py
tests/test_udp_client.py
blueye_legacyprotocol-1.0.0.dist-info/METADATA
blueye_legacyprotocol-1.0.0.dist-info/WHEEL
blueye_legacyprotocol-1.0.0.dist-info/top_level.txt
blueye_legacyprotocol-1.0.0.dist-info/RECORD
