Metadata-Version: 2.4
Name: blueye.legacyprotocol
Version: 1.0.0
Summary: Legacy UDP/TCP protocol for Blueye drones
Author-email: Blueye Robotics <contact@blueye.no>
License:                    GNU LESSER GENERAL PUBLIC LICENSE
Requires-Python: <4,>=3.10
License-File: LICENSE
Requires-Dist: numpy~=2.2
Dynamic: license-file
